dottify/__init__.py
dottify/__version__.py
dottify/dottify.py
dottify/exceptions.py
dottify-1.1.3.dist-info/licenses/LICENSE
dottify-1.1.3.dist-info/METADATA
dottify-1.1.3.dist-info/WHEEL
dottify-1.1.3.dist-info/top_level.txt
dottify-1.1.3.dist-info/RECORD
