Metadata-Version: 2.4
Name: dottify
Version: 1.1.3
Summary: A Python library to access dictionaries using dot notation.
Home-page: https://github.com/nanaelie/dottify
Author: nae.dev
Author-email: nae.devp@gmail.com
License: MIT
Project-URL: Source, https://github.com/nanaelie/dottify
Project-URL: Bug Tracker, https://github.com/nanaelie/dottify/issues
Project-URL: Documentation, https://github.com/nanaelie/dottify#readme
Classifier: Programming Language :: Python :: 3
Classifier: License :: OSI Approved :: MIT License
Classifier: Operating System :: OS Independent
Classifier: Development Status :: 5 - Production/Stable
Classifier: Intended Audience :: Developers
Classifier: Topic :: Software Development :: Libraries
Requires-Python: >=3.6
License-File: LICENSE
Provides-Extra: dev
Requires-Dist: pytest; extra == "dev"
Dynamic: author
Dynamic: author-email
Dynamic: classifier
Dynamic: description
Dynamic: description-content-type
Dynamic: home-page
Dynamic: license
Dynamic: license-file
Dynamic: project-url
Dynamic: provides-extra
Dynamic: requires-python
Dynamic: summary
